LICENSE.md
README.md
orbit_component_vcheck/.gitignore
orbit_component_vcheck/__init__.py
orbit_component_vcheck/plugin.py
orbit_component_vcheck/schema/Versions.py
orbit_component_vcheck/src/versions.py
orbit_component_vcheck-1.0.22.dist-info/LICENSE.md
orbit_component_vcheck-1.0.22.dist-info/METADATA
orbit_component_vcheck-1.0.22.dist-info/WHEEL
orbit_component_vcheck-1.0.22.dist-info/RECORD
